pydantic_ai_bedrock/__init__.py
pydantic_ai_bedrock/bedrock.py
pydantic_ai_bedrock/py.typed
pydantic_ai_bedrock-0.2.2.dist-info/METADATA
pydantic_ai_bedrock-0.2.2.dist-info/WHEEL
pydantic_ai_bedrock-0.2.2.dist-info/licenses/LICENSE
pydantic_ai_bedrock-0.2.2.dist-info/RECORD
